{
    "op": {
        "upvote_ratio": null,
        "selftext": "",
        "title": "Breaking Antivirus Software - SyScan360 2014 [PDF]",
        "score": 8,
        "id": "2bx2nf",
        "commsNum": 0,
        "timeStamp": "2014/07/27-21:51:50",
        "author_name": "chubbymaggie",
        "is_self": false,
        "locked": null,
        "num_comments": 0,
        "over_18": false,
        "spoiler": null,
        "subreddit": "malware",
        "stickied": false,
        "url": "http://www.syscan360.org/slides/2014_EN_BreakingAVSoftware_JoxeanKoret.pdf"
    },
    "posts": {}
}