{
    "op": {
        "upvote_ratio": null,
        "selftext": "",
        "title": "Help removing malware",
        "score": 1,
        "id": "2ieufc",
        "commsNum": 0,
        "timeStamp": "2014/10/05-19:37:22",
        "author_name": "[deleted]",
        "is_self": true,
        "locked": null,
        "num_comments": 0,
        "over_18": false,
        "spoiler": null,
        "subreddit": "malware",
        "stickied": false,
        "url": "http://www.reddit.com/r/Malware/comments/2ieufc/help_removing_malware/"
    },
    "posts": {}
}