{
    "op": {
        "upvote_ratio": null,
        "selftext": "",
        "title": "Interesting: Infection in North Korea!",
        "score": 27,
        "id": "2y0dke",
        "commsNum": 10,
        "timeStamp": "2015/03/05-02:36:53",
        "author_name": "VirusTracker",
        "is_self": false,
        "locked": null,
        "num_comments": 10,
        "over_18": false,
        "spoiler": null,
        "subreddit": "malware",
        "stickied": false,
        "url": "http://virustracker.net/175.45.177.138"
    },
    "posts": {}
}