{
    "op": {
        "upvote_ratio": null,
        "selftext": "",
        "title": "https://teksecurityblog.com/blog/2015/03/25/4-ransomware-lessons-you-need-to-learn-before-it-snags-you/",
        "score": 1,
        "id": "309wxj",
        "commsNum": 1,
        "timeStamp": "2015/03/25-10:44:35",
        "author_name": "teksquisite",
        "is_self": false,
        "locked": null,
        "num_comments": 1,
        "over_18": false,
        "spoiler": null,
        "subreddit": "malware",
        "stickied": false,
        "url": "http://teksqu.com/Tf4x3X6"
    },
    "posts": {}
}