{
    "op": {
        "upvote_ratio": null,
        "selftext": "",
        "title": "On the other side of CTB-Locker : the Affiliate server.",
        "score": 8,
        "id": "376sps",
        "commsNum": 0,
        "timeStamp": "2015/05/25-03:09:59",
        "author_name": "GelosSnake",
        "is_self": false,
        "locked": null,
        "num_comments": 0,
        "over_18": false,
        "spoiler": null,
        "subreddit": "malware",
        "stickied": false,
        "url": "http://malware.dontneedcoffee.com/2015/05/on-other-side-of-ctb-locker-affiliate.html"
    },
    "posts": {}
}