{
    "op": {
        "upvote_ratio": null,
        "selftext": "",
        "title": "Verwijder Locker v2.7, Hoe Locker v2.7 Effectief Te Verwijderen",
        "score": 1,
        "id": "399syz",
        "commsNum": 0,
        "timeStamp": "2015/06/10-00:47:17",
        "author_name": "jamesbond9657",
        "is_self": false,
        "locked": null,
        "num_comments": 0,
        "over_18": false,
        "spoiler": null,
        "subreddit": "malware",
        "stickied": false,
        "url": "http://www.infowine.org/verwijderenmalware/verwijder-locker-v2-7-hoe-locker-v2-7-effectief-te-verwijderen"
    },
    "posts": {}
}