{
    "op": {
        "upvote_ratio": null,
        "selftext": "",
        "title": "Disinstallare klit.startnow.com: via pi\u00f9 semplice per sbarazzarsi di klit.startnow.com - Del Malware Rimozione Guida",
        "score": 1,
        "id": "399ux7",
        "commsNum": 0,
        "timeStamp": "2015/06/10-01:13:03",
        "author_name": "parkersmith13",
        "is_self": false,
        "locked": null,
        "num_comments": 0,
        "over_18": false,
        "spoiler": null,
        "subreddit": "malware",
        "stickied": false,
        "url": "http://www.virusspywaredisinstallazione.com/disinstallare-klit-startnow-com-via-piu-semplice-per-sbarazzarsi-di-klit-startnow-com"
    },
    "posts": {}
}