{
    "op": {
        "upvote_ratio": null,
        "selftext": "",
        "title": "Rimuovere \u00e2\u0080\u00990800 FIXMYPC\u00e2\u0080\u0099 Pop-Ups, Come Rimuovere Efficacemente \u00e2\u0080\u00990800 FIXMYPC\u00e2\u0080\u0099 Pop-Ups - Cancellare Malware Da Windows",
        "score": 1,
        "id": "3a0na1",
        "commsNum": 0,
        "timeStamp": "2015/06/16-01:25:54",
        "author_name": "parkersmith13",
        "is_self": false,
        "locked": null,
        "num_comments": 0,
        "over_18": false,
        "spoiler": null,
        "subreddit": "malware",
        "stickied": false,
        "url": "http://www.infowine.org/cancellaremalware/rimuovere-a%c2%80%c2%990800-fixmypca%c2%80%c2%99-pop-ups-come-rimuovere-efficacemente-a%c2%80%c2%990800-fixmypca%c2%80%c2%99-pop-ups"
    },
    "posts": {}
}