{
    "op": {
        "upvote_ratio": null,
        "selftext": "",
        "title": "Borrar Yousoftver.com pop-ups (Adware Pasos De Desinstalacion)",
        "score": 1,
        "id": "3bpt3y",
        "commsNum": 0,
        "timeStamp": "2015/06/30-21:25:25",
        "author_name": "vaylo",
        "is_self": false,
        "locked": null,
        "num_comments": 0,
        "over_18": false,
        "spoiler": null,
        "subreddit": "malware",
        "stickied": false,
        "url": "http://es.allcopts.com/2015/06/30/borrar-yousoftver-com-pop-ups-adware-pasos-de-desinstalacion/"
    },
    "posts": {}
}