{
    "op": {
        "upvote_ratio": null,
        "selftext": "",
        "title": "Borrar Best Price Ninja (Adware Pasos De Desinstalacion)",
        "score": 1,
        "id": "3cihba",
        "commsNum": 0,
        "timeStamp": "2015/07/07-21:10:24",
        "author_name": "vaylo",
        "is_self": false,
        "locked": null,
        "num_comments": 0,
        "over_18": false,
        "spoiler": null,
        "subreddit": "malware",
        "stickied": false,
        "url": "http://es.allcopts.com/2015/07/07/borrar-best-price-ninja-adware-pasos-de-desinstalacion/"
    },
    "posts": {}
}