{
    "op": {
        "upvote_ratio": null,
        "selftext": "",
        "title": "Verwijder Backdoor.NanoCore, Hoe Backdoor.NanoCore Volledig Te Verwijderen",
        "score": 1,
        "id": "3fe59o",
        "commsNum": 0,
        "timeStamp": "2015/08/01-02:35:17",
        "author_name": "jamesbond9657",
        "is_self": false,
        "locked": null,
        "num_comments": 0,
        "over_18": false,
        "spoiler": null,
        "subreddit": "malware",
        "stickied": false,
        "url": "http://www.infowine.org/verwijderenmalware/verwijder-backdoor-nanocore-hoe-backdoor-nanocore-volledig-te-verwijderen"
    },
    "posts": {}
}