{
    "op": {
        "upvote_ratio": null,
        "selftext": "",
        "title": "Quick Q&amp;A with Author of Mabouia, First Mac OS X Ransomware",
        "score": 3,
        "id": "3ros5j",
        "commsNum": 0,
        "timeStamp": "2015/11/05-14:32:51",
        "author_name": "campuscodi",
        "is_self": false,
        "locked": false,
        "num_comments": 0,
        "over_18": false,
        "spoiler": null,
        "subreddit": "malware",
        "stickied": false,
        "url": "http://news.softpedia.com/news/quick-q-a-with-author-of-mabouia-first-mac-os-x-ransomware-495795.shtml"
    },
    "posts": {}
}