{
    "op": {
        "upvote_ratio": null,
        "selftext": "",
        "title": "Cryptowall 4.0 comes from Russia, Bitdefender released a vaccine",
        "score": 1,
        "id": "3s5348",
        "commsNum": 0,
        "timeStamp": "2015/11/09-07:15:32",
        "author_name": "securityaffairs",
        "is_self": false,
        "locked": false,
        "num_comments": 0,
        "over_18": false,
        "spoiler": null,
        "subreddit": "malware",
        "stickied": false,
        "url": "http://securityaffairs.co/wordpress/41862/cyber-crime/cryptowall-4-0-russia-vaccine.html"
    },
    "posts": {}
}