{
    "op": {
        "upvote_ratio": null,
        "selftext": "",
        "title": "EFF gets control of ElectronicFrontierFoundation.org which was being used for nefarious purposes.",
        "score": 34,
        "id": "3t8n58",
        "commsNum": 3,
        "timeStamp": "2015/11/17-17:59:27",
        "author_name": "k3vb0tn3t",
        "is_self": false,
        "locked": false,
        "num_comments": 3,
        "over_18": false,
        "spoiler": null,
        "subreddit": "malware",
        "stickied": false,
        "url": "http://www.theregister.co.uk/2015/11/18/eff_malware_domain/"
    },
    "posts": {}
}