{
    "op": {
        "upvote_ratio": null,
        "selftext": "",
        "title": "Trojan.Boaxxe.C Entfernen, Wie Trojan.Boaxxe.C Vollst\u00e4ndig Zu Entfernen - L\u00f6schen Malware Von Windows",
        "score": 1,
        "id": "3uytgg",
        "commsNum": 0,
        "timeStamp": "2015/11/30-22:20:11",
        "author_name": "stevemartine01",
        "is_self": false,
        "locked": false,
        "num_comments": 0,
        "over_18": false,
        "spoiler": null,
        "subreddit": "malware",
        "stickied": false,
        "url": "http://www.infowine.org/loschenmalware/trojan-boaxxe-c-entfernen-wie-trojan-boaxxe-c-vollstandig-zu-entfernen"
    },
    "posts": {}
}