{
    "op": {
        "upvote_ratio": null,
        "selftext": "",
        "title": "Decrypt Teslacrypt and Remove Teslacrypt Ransomware [Update]",
        "score": 1,
        "id": "41tlfh",
        "commsNum": 0,
        "timeStamp": "2016/01/20-01:14:52",
        "author_name": "dangelost",
        "is_self": false,
        "locked": false,
        "num_comments": 0,
        "over_18": false,
        "spoiler": null,
        "subreddit": "malware",
        "stickied": false,
        "url": "http://virusguides.com/decrypt-teslacrypt/"
    },
    "posts": {}
}