{
    "op": {
        "upvote_ratio": null,
        "selftext": "[deleted]",
        "title": "What is this malicious (?) Javascript doing ?",
        "score": 5,
        "id": "477sop",
        "commsNum": 3,
        "timeStamp": "2016/02/23-09:51:41",
        "author_name": "[deleted]",
        "is_self": true,
        "locked": false,
        "num_comments": 3,
        "over_18": false,
        "spoiler": null,
        "subreddit": "malware",
        "stickied": false,
        "url": "https://www.reddit.com/r/Malware/comments/477sop/what_is_this_malicious_javascript_doing/"
    },
    "posts": {}
}