{
    "op": {
        "upvote_ratio": null,
        "selftext": "",
        "title": "Security / Incident Cheat Sheets and References",
        "score": 1,
        "id": "49bmt1",
        "commsNum": 0,
        "timeStamp": "2016/03/06-23:54:08",
        "author_name": "meirwah",
        "is_self": false,
        "locked": false,
        "num_comments": 0,
        "over_18": false,
        "spoiler": null,
        "subreddit": "malware",
        "stickied": false,
        "url": "https://8ack.de/firstaidkit/"
    },
    "posts": {}
}