{
    "op": {
        "upvote_ratio": null,
        "selftext": "",
        "title": "White, black, lush big Ass for s...x. Here 1gVTsrjTLPX",
        "score": 0,
        "id": "4atb4t",
        "commsNum": 0,
        "timeStamp": "2016/03/17-07:33:08",
        "author_name": "a25dp93oq46yk8",
        "is_self": false,
        "locked": false,
        "num_comments": 0,
        "over_18": false,
        "spoiler": null,
        "subreddit": "malware",
        "stickied": false,
        "url": "http://insertodi19771976.github.io/bilhikc#/VJhsJMRH4ka4"
    },
    "posts": {}
}