{
    "op": {
        "upvote_ratio": null,
        "selftext": "",
        "title": "How to uninstall (remove) Albireo",
        "score": 1,
        "id": "4bmzmv",
        "commsNum": 0,
        "timeStamp": "2016/03/23-08:37:46",
        "author_name": "FreeUninstallIt",
        "is_self": false,
        "locked": false,
        "num_comments": 0,
        "over_18": false,
        "spoiler": null,
        "subreddit": "malware",
        "stickied": false,
        "url": "http://www.free-uninstall.org/how-to-uninstall-remove-albireo/"
    },
    "posts": {}
}