{
    "op": {
        "upvote_ratio": null,
        "selftext": "[deleted]",
        "title": "Kaspersky reporting svhost.exe",
        "score": 0,
        "id": "4g49vb",
        "commsNum": 3,
        "timeStamp": "2016/04/23-10:00:03",
        "author_name": "[deleted]",
        "is_self": true,
        "locked": false,
        "num_comments": 3,
        "over_18": false,
        "spoiler": null,
        "subreddit": "malware",
        "stickied": false,
        "url": "https://www.reddit.com/r/Malware/comments/4g49vb/kaspersky_reporting_svhostexe/"
    },
    "posts": {}
}