{
    "op": {
        "upvote_ratio": null,
        "selftext": "",
        "title": "Free Guide and Tool To Remove Safensecure.com-allsites3.xyz",
        "score": 1,
        "id": "5fvmeo",
        "commsNum": 0,
        "timeStamp": "2016/12/01-00:59:31",
        "author_name": "removevirusbrowser",
        "is_self": false,
        "locked": false,
        "num_comments": 0,
        "over_18": false,
        "spoiler": false,
        "subreddit": "malware",
        "stickied": false,
        "url": "http://removevirusfrombrowser.com/remove-safensecure-com-allsites3-xyz"
    },
    "posts": {}
}