{
    "op": {
        "upvote_ratio": null,
        "selftext": "",
        "title": "Remove ww12.shellsband.com From Windows",
        "score": 1,
        "id": "5jqdx2",
        "commsNum": 0,
        "timeStamp": "2016/12/22-04:45:05",
        "author_name": "removevirusbrowser",
        "is_self": false,
        "locked": false,
        "num_comments": 0,
        "over_18": false,
        "spoiler": false,
        "subreddit": "malware",
        "stickied": false,
        "url": "https://removevirusfromwindows.com/remove-ww12-shellsband-com"
    },
    "posts": {}
}