{
    "op": {
        "upvote_ratio": null,
        "selftext": "",
        "title": "Get Rid Of 1-844-526-1405 pop-up",
        "score": 1,
        "id": "5m4p0x",
        "commsNum": 0,
        "timeStamp": "2017/01/04-21:57:30",
        "author_name": "removevirusbrowser",
        "is_self": false,
        "locked": false,
        "num_comments": 0,
        "over_18": false,
        "spoiler": false,
        "subreddit": "malware",
        "stickied": false,
        "url": "https://removevirusfromwindows.com/remove-1-844-526-1405-pop-up"
    },
    "posts": {}
}