{
    "op": {
        "upvote_ratio": null,
        "selftext": "I received some photos from someone and I am worried that he might have infected them with malware. If I upload them to google drive, will it be automatically detected if they contain malware? Is it safe to download them from google drive to my hard disk later?",
        "title": "Does Google Drive automatically detect malware in files?",
        "score": 6,
        "id": "5nm1fh",
        "commsNum": 12,
        "timeStamp": "2017/01/12-13:09:32",
        "author_name": "judith33",
        "is_self": true,
        "locked": false,
        "num_comments": 12,
        "over_18": false,
        "spoiler": false,
        "subreddit": "malware",
        "stickied": false,
        "url": "https://www.reddit.com/r/Malware/comments/5nm1fh/does_google_drive_automatically_detect_malware_in/"
    },
    "posts": {}
}