{
    "op": {
        "upvote_ratio": null,
        "selftext": "",
        "title": "Uninstall 1-844-816-7270 Pop-up virus to Solve your Systems Problem Now",
        "score": 1,
        "id": "5oaerh",
        "commsNum": 0,
        "timeStamp": "2017/01/16-03:41:51",
        "author_name": "RemoveMalwarethreats",
        "is_self": false,
        "locked": false,
        "num_comments": 0,
        "over_18": false,
        "spoiler": false,
        "subreddit": "malware",
        "stickied": false,
        "url": "https://removevirusfromwindows.com/remove-1-844-816-7270-pop-up-virus"
    },
    "posts": {}
}