{
    "op": {
        "upvote_ratio": null,
        "selftext": "",
        "title": "How to remove Ransom.Hermes completely (removal guide)",
        "score": 1,
        "id": "5v6z6q",
        "commsNum": 0,
        "timeStamp": "2017/02/20-12:30:58",
        "author_name": "mick01jones",
        "is_self": false,
        "locked": false,
        "num_comments": 0,
        "over_18": false,
        "spoiler": false,
        "subreddit": "malware",
        "stickied": false,
        "url": "http://www.threatremovalsite.com/how-to-remove-ransom-hermes-completely-removal-guide/"
    },
    "posts": {}
}