{
    "op": {
        "upvote_ratio": null,
        "selftext": "",
        "title": "Week 8 in Information Security, 2017",
        "score": 6,
        "id": "5wf7y0",
        "commsNum": 1,
        "timeStamp": "2017/02/26-22:25:04",
        "author_name": "undercomm",
        "is_self": false,
        "locked": false,
        "num_comments": 1,
        "over_18": false,
        "spoiler": false,
        "subreddit": "malware",
        "stickied": false,
        "url": "https://www.malgregator.com/week-08-2017.html"
    },
    "posts": {}
}