{
    "op": {
        "upvote_ratio": null,
        "selftext": "[removed]",
        "title": "P2P UDP Botnets - Which are existing today?",
        "score": 1,
        "id": "64o878",
        "commsNum": 0,
        "timeStamp": "2017/04/10-19:41:58",
        "author_name": "Aloa1",
        "is_self": true,
        "locked": false,
        "num_comments": 0,
        "over_18": false,
        "spoiler": false,
        "subreddit": "malware",
        "stickied": false,
        "url": "https://www.reddit.com/r/Malware/comments/64o878/p2p_udp_botnets_which_are_existing_today/"
    },
    "posts": {}
}