{
    "op": {
        "upvote_ratio": null,
        "selftext": "Hi,\n\nDoes anybody have samples of possible new wanacry variants without the kill switch?\nreference here: https://motherboard.vice.com/en_us/article/round-two-wannacry-ransomware-that-struck-the-globe-is-back?utm_content=buffere2fbe&amp;utm_medium=social&amp;utm_source=twitter.com&amp;utm_campaign=buffer",
        "title": "Looking for samples of wanacry without the kill switch",
        "score": 2,
        "id": "6b0vh2",
        "commsNum": 3,
        "timeStamp": "2017/05/13-16:23:05",
        "author_name": "peter_mack",
        "is_self": true,
        "locked": false,
        "num_comments": 3,
        "over_18": false,
        "spoiler": false,
        "subreddit": "malware",
        "stickied": false,
        "url": "https://www.reddit.com/r/Malware/comments/6b0vh2/looking_for_samples_of_wanacry_without_the_kill/"
    },
    "posts": {}
}