{
    "op": {
        "upvote_ratio": null,
        "selftext": "",
        "title": "Stegano Exploit Kit now uses the Diffie-Hellman Algorithm",
        "score": 1,
        "id": "6cc9pu",
        "commsNum": 0,
        "timeStamp": "2017/05/20-12:36:10",
        "author_name": "securityaffairs",
        "is_self": false,
        "locked": false,
        "num_comments": 0,
        "over_18": false,
        "spoiler": false,
        "subreddit": "malware",
        "stickied": false,
        "url": "http://securityaffairs.co/wordpress/59284/malware/stegano-exploit-kit-diffie-hellman.html"
    },
    "posts": {}
}