{
    "op": {
        "upvote_ratio": null,
        "selftext": "[deleted]",
        "title": "Reversing Malware: CoinMiner",
        "score": 1,
        "id": "6qgabf",
        "commsNum": 0,
        "timeStamp": "2017/07/30-01:01:37",
        "author_name": "[deleted]",
        "is_self": false,
        "locked": false,
        "num_comments": 0,
        "over_18": false,
        "spoiler": false,
        "subreddit": "malware",
        "stickied": false,
        "url": "https://secrary.com/ReversingMalware/CoinMiner/"
    },
    "posts": {}
}