{
    "op": {
        "upvote_ratio": null,
        "selftext": "[removed]",
        "title": "Sample Request Spider Ransomware Document",
        "score": 1,
        "id": "8nbi0q",
        "commsNum": 0,
        "timeStamp": "2018/05/30-12:34:16",
        "author_name": "Wreckagekc",
        "is_self": true,
        "locked": false,
        "num_comments": 0,
        "over_18": false,
        "spoiler": false,
        "subreddit": "malware",
        "stickied": false,
        "url": "https://www.reddit.com/r/Malware/comments/8nbi0q/sample_request_spider_ransomware_document/"
    },
    "posts": {}
}