{
    "op": {
        "upvote_ratio": null,
        "selftext": "",
        "title": "Advanced Malware vs. Malware: How to Protect Your Enterprise from Both",
        "score": 1,
        "id": "977mkx",
        "commsNum": 0,
        "timeStamp": "2018/08/14-04:42:19",
        "author_name": "sophiacart",
        "is_self": false,
        "locked": false,
        "num_comments": 0,
        "over_18": false,
        "spoiler": false,
        "subreddit": "malware",
        "stickied": false,
        "url": "http://isc2central.blogspot.com/2018/08/advanced-malware-vs-malware-how-to.html"
    },
    "posts": {}
}