{
    "op": {
        "upvote_ratio": null,
        "selftext": "",
        "title": "Way to uninstall .Bz Ransomware virus from your system easily",
        "score": 1,
        "id": "blp5bi",
        "commsNum": 0,
        "timeStamp": "2019/05/07-03:41:06",
        "author_name": "emmaparker817",
        "is_self": false,
        "locked": false,
        "num_comments": 0,
        "over_18": false,
        "spoiler": false,
        "subreddit": "malware",
        "stickied": false,
        "url": "http://blog.reimage.us.com/uninstall-bz-ransomware-virus"
    },
    "posts": {}
}