{
    "op": {
        "upvote_ratio": null,
        "selftext": "",
        "title": "How to remove [Btcdecoding@qq.com].dqb ransomware virus from PC",
        "score": 1,
        "id": "cepf8m",
        "commsNum": 0,
        "timeStamp": "2019/07/18-00:43:20",
        "author_name": "emmaparker817",
        "is_self": false,
        "locked": false,
        "num_comments": 0,
        "over_18": false,
        "spoiler": false,
        "subreddit": "malware",
        "stickied": false,
        "url": "http://blog.reimage.us.com/remove-btcdecodingqq-com-dqb-ransomware-virus"
    },
    "posts": {}
}