{
    "op": {
        "upvote_ratio": null,
        "selftext": "",
        "title": "Fake Ad Blockers 2: Now with Cookies and Ad Fraud",
        "score": 31,
        "id": "d6i9cg",
        "commsNum": 0,
        "timeStamp": "2019/09/19-11:35:45",
        "author_name": "g0relics",
        "is_self": false,
        "locked": false,
        "num_comments": 0,
        "over_18": false,
        "spoiler": false,
        "subreddit": "malware",
        "stickied": false,
        "url": "https://adguard.com/en/blog/fake-ad-blockers-part-2.html"
    },
    "posts": {}
}