{
    "op": {
        "upvote_ratio": null,
        "selftext": "",
        "title": "Role of Artificial Intelligence in Strengthening Cybersecurity",
        "score": 1,
        "id": "dj8hwq",
        "commsNum": 0,
        "timeStamp": "2019/10/17-09:06:19",
        "author_name": "Firdosali001",
        "is_self": false,
        "locked": false,
        "num_comments": 0,
        "over_18": false,
        "spoiler": false,
        "subreddit": "malware",
        "stickied": false,
        "url": "https://medium.com/@Oodles_AI/role-of-artificial-intelligence-in-strengthening-cybersecurity-4b8651a0d2f9"
    },
    "posts": {}
}