{
    "op": {
        "upvote_ratio": 1.0,
        "selftext": "",
        "title": "New World Government \u2013 AI &amp;#8211; Big Pharma \u2013 Global Warming \u2013 UFOs &amp;#8211; Spirituality",
        "score": 1,
        "id": "jiqhd7",
        "commsNum": 0,
        "timeStamp": "2020/10/26-17:00:24",
        "author_name": "MelanieEastwood",
        "is_self": false,
        "locked": false,
        "num_comments": 0,
        "over_18": false,
        "spoiler": false,
        "subreddit": "malware",
        "stickied": false,
        "url": "https://asahiramen.com"
    },
    "posts": {}
}