{
    "op": {
        "upvote_ratio": 1.0,
        "selftext": "",
        "title": "Risk of Phishing Attacks and Malware Downloads from Visiting Adult Websites - WebTitan DNS Filter",
        "score": 1,
        "id": "qgqstu",
        "commsNum": 0,
        "timeStamp": "2021/10/27-00:08:08",
        "author_name": "AdvertisingMajor6010",
        "is_self": false,
        "locked": false,
        "num_comments": 0,
        "over_18": false,
        "spoiler": false,
        "subreddit": "malware",
        "stickied": false,
        "url": "https://www.webtitan.com/blog/risk-phishing-malware-downloads-from-visiting-adult-websites/"
    },
    "posts": {}
}