{
    "op": {
        "upvote_ratio": 1.0,
        "selftext": "",
        "title": "r/Malware Subdirect Statistics",
        "score": 1,
        "id": "rpj7g9",
        "commsNum": 0,
        "timeStamp": "2021/12/27-00:56:18",
        "author_name": "lochydjango",
        "is_self": false,
        "locked": false,
        "num_comments": 0,
        "over_18": false,
        "spoiler": false,
        "subreddit": "malware",
        "stickied": false,
        "url": "https://redditpagematrics.com/r/Malware"
    },
    "posts": {}
}