{
    "op": {
        "upvote_ratio": 1.0,
        "selftext": "",
        "title": "A fake Android Flash Player app contains dangerous malware",
        "score": 1,
        "id": "s0np43",
        "commsNum": 0,
        "timeStamp": "2022/01/10-08:17:19",
        "author_name": "amancoreseg",
        "is_self": false,
        "locked": false,
        "num_comments": 0,
        "over_18": false,
        "spoiler": false,
        "subreddit": "malware",
        "stickied": false,
        "url": "https://www.realmicentral.com/2022/01/10/a-fake-android-flash-player-app-contains-dangerous-malware/"
    },
    "posts": {}
}