{
    "op": {
        "upvote_ratio": 1.0,
        "selftext": "&amp;#x200B;\n\nhttps://preview.redd.it/0uwwmcz1o7d81.png?width=306&amp;format=png&amp;auto=webp&amp;s=c44924d68ca0ca310a2b2a6554d1cd55dbf94594\n\nFirst google search says it is prob a virus",
        "title": "Found this on a phone",
        "score": 1,
        "id": "s9z3cc",
        "commsNum": 0,
        "timeStamp": "2022/01/22-01:49:55",
        "author_name": "Lonely-Ebb_",
        "is_self": true,
        "locked": false,
        "num_comments": 0,
        "over_18": false,
        "spoiler": false,
        "subreddit": "malware",
        "stickied": false,
        "url": "https://www.reddit.com/r/Malware/comments/s9z3cc/found_this_on_a_phone/"
    },
    "posts": {
        "hupbcwu": {
            "comment": "i meant the app called im.thebot.messenger",
            "timeStamp": "2022/01/29-01:48:04",
            "id": "hupbcwu",
            "is_submitter": true,
            "link_id": "t3_s9z3cc",
            "parent_id": "t1_hu8fqgc",
            "score": 1,
            "stickied": false,
            "author_name": "Lonely-Ebb_"
        },
        "huksxoc": {
            "comment": "[removed]",
            "timeStamp": "2022/01/28-05:07:40",
            "id": "huksxoc",
            "is_submitter": false,
            "link_id": "t3_s9z3cc",
            "parent_id": "t1_hu8fqgc",
            "score": 1,
            "stickied": false,
            "author_name": "[deleted]"
        },
        "htul0vt": {
            "comment": "you serious?!?!\n\nwth",
            "timeStamp": "2022/01/22-22:12:14",
            "id": "htul0vt",
            "is_submitter": true,
            "link_id": "t3_s9z3cc",
            "parent_id": "t1_htq9zl4",
            "score": 1,
            "stickied": false,
            "author_name": "Lonely-Ebb_"
        },
        "htq9zl4": {
            "comment": "Nice find detective, my boys at the lab have traced it back to russia",
            "timeStamp": "2022/01/22-02:54:51",
            "id": "htq9zl4",
            "is_submitter": false,
            "link_id": "t3_s9z3cc",
            "parent_id": "t3_s9z3cc",
            "score": 1,
            "stickied": false,
            "author_name": "SpookyWA"
        },
        "htq6bpq": {
            "comment": "[removed]",
            "timeStamp": "2022/01/22-02:09:51",
            "id": "htq6bpq",
            "is_submitter": false,
            "link_id": "t3_s9z3cc",
            "parent_id": "t3_s9z3cc",
            "score": 1,
            "stickied": false,
            "author_name": "[deleted]"
        }
    }
}