{
    "op": {
        "upvote_ratio": 1.0,
        "selftext": "[removed]",
        "title": "Is the information on my computer safe now?",
        "score": 1,
        "id": "u4lr8w",
        "commsNum": 0,
        "timeStamp": "2022/04/15-17:27:39",
        "author_name": "Ukihigo12",
        "is_self": true,
        "locked": false,
        "num_comments": 0,
        "over_18": false,
        "spoiler": false,
        "subreddit": "malware",
        "stickied": false,
        "url": "https://www.reddit.com/r/Malware/comments/u4lr8w/is_the_information_on_my_computer_safe_now/"
    },
    "posts": {}
}